dpydevtools/__init__.py
dpydevtools/constants.py
dpydevtools/enums.py
dpydevtools/exceptions.py
dpydevtools/parser.py
dpydevtools/tools.py
dpydevtools/utils.py
dpy_devtools-0.0.3.dist-info/LICENSE
dpy_devtools-0.0.3.dist-info/METADATA
dpy_devtools-0.0.3.dist-info/WHEEL
dpy_devtools-0.0.3.dist-info/top_level.txt
dpy_devtools-0.0.3.dist-info/RECORD
