Metadata-Version: 2.1
Name: dpy-devtools
Version: 0.0.3
Summary: A set of useful administrator and developer tools for discord.py
Author-email: "Tanner B. Corcoran" <tannerbcorcoran@gmail.com>
Project-URL: Homepage, https://github.com/tanrbobanr/dpy-devtools
Classifier: Programming Language :: Python :: 3
Classifier: License :: OSI Approved :: MIT License
Classifier: Operating System :: OS Independent
Requires-Python: >=3.11
License-File: LICENSE
Requires-Dist: discord.py (>=2.0.0)
